odoo/addons/account_receipt_sale/README.rst
odoo/addons/account_receipt_sale/__init__.py
odoo/addons/account_receipt_sale/__manifest__.py
odoo/addons/account_receipt_sale/i18n/account_receipt_sale.pot
odoo/addons/account_receipt_sale/i18n/es.po
odoo/addons/account_receipt_sale/i18n/it.po
odoo/addons/account_receipt_sale/migrations/14.0.1.0.1/post-migrate.py
odoo/addons/account_receipt_sale/models/__init__.py
odoo/addons/account_receipt_sale/models/sale.py
odoo/addons/account_receipt_sale/readme/CONFIGURE.rst
odoo/addons/account_receipt_sale/readme/CONTRIBUTORS.rst
odoo/addons/account_receipt_sale/readme/DESCRIPTION.rst
odoo/addons/account_receipt_sale/readme/HISTORY.rst
odoo/addons/account_receipt_sale/static/description/icon.png
odoo/addons/account_receipt_sale/static/description/index.html
odoo/addons/account_receipt_sale/tests/__init__.py
odoo/addons/account_receipt_sale/tests/test_receipts.py
odoo/addons/account_receipt_sale/views/sale_views.xml
odoo/addons/account_receipt_sale/wizard/__init__.py
odoo/addons/account_receipt_sale/wizard/sale_make_invoice.py
odoo14_addon_account_receipt_sale-14.0.1.0.2.dev8.dist-info/METADATA
odoo14_addon_account_receipt_sale-14.0.1.0.2.dev8.dist-info/WHEEL
odoo14_addon_account_receipt_sale-14.0.1.0.2.dev8.dist-info/top_level.txt
odoo14_addon_account_receipt_sale-14.0.1.0.2.dev8.dist-info/RECORD
