Metadata-Version: 2.1
Name: odoo14-addon-account_receipt_sale
Version: 14.0.1.0.2.dev8
Summary: Generate receipts from sale orders
Home-page: https://github.com/OCA/account-invoicing
Author: TAKOBI, Agile Business Group, Odoo Community Association (OCA)
Author-email: support@odoo-community.org
License: AGPL-3
Classifier: Programming Language :: Python
Classifier: Framework :: Odoo
Classifier: Framework :: Odoo :: 14.0
Classifier: License :: OSI Approved :: GNU Affero General Public License v3
Classifier: Development Status :: 4 - Beta
Requires-Python: >=3.6
Requires-Dist: odoo14-addon-account-receipt-base
Requires-Dist: odoo14-addon-account-receipt-journal
Requires-Dist: odoo<14.1dev,>=14.0a
Requires-Dist: openupgradelib
